<?xml version="1.0" encoding="UTF-8"?>
<config-list>
    <!-- GENDER -->
    <genders>
        <name>Male</name>
        <gender>1</gender>
    </genders>

    <!-- HEADS -->
    <heads>
        <name>Male C Head</name>
        <model>assets/models/collada/Heads/MaleHead/MaleCHead.bhf</model>
    </heads>
    <heads>
        <name>Black Head</name>
        <model>assets/models/collada/Heads/MaleHead/blackHead.bhf</model>
    </heads>
    <heads>
        <name>FaceGen Hi-Poly Head</name>
        <model>assets/models/collada/Heads/MaleHead/FaceGenMaleHi.bhf</model>
    </heads>
    <heads>
        <name>FaceGen Medium-Poly Head</name>
        <model>assets/models/collada/Heads/MaleHead/FG_Male02MedPoly.bhf</model>
    </heads>
    <heads>
        <name>FaceGen Medium-Poly Head 2</name>
        <model>assets/models/collada/Heads/MaleHead/FG_MaleHead02Medium.bhf</model>
    </heads>
    <heads>
        <name>FaceGen Low-Poly Head</name>
        <model>assets/models/collada/Heads/MaleHead/FG_MaleLowPoly_01.bhf</model>
    </heads>
    <!--
    <heads>
        <name>Obama Head</name>
        <model>assets/models/collada/Heads/MaleHead/FG_Obama_HeadMedPoly.bhf</model>
    </heads>
    -->

    <!-- HAIR -->
    <hair>
        <name>Male_PonyTailShape</name>
        <model>assets/models/collada/Hair/MaleHair/FG_Male01HairDefaults.dae</model>
        <shapes>Male_PonyTailShape</shapes>
    </hair>
    <hair>
        <name>Male_ChinLengthPartLeftShape</name>
        <model>assets/models/collada/Hair/MaleHair/FG_Male01HairDefaults.dae</model>
        <shapes>Male_ChinLengthPartLeftShape</shapes>
    </hair>
    <hair>
        <name>Male_SlickedBackShape</name>
        <model>assets/models/collada/Hair/MaleHair/FG_Male01HairDefaults.dae</model>
        <shapes>Male_SlickedBackShape</shapes>
    </hair>
    <hair>
        <name>Male_PartLeftShape</name>
        <model>assets/models/collada/Hair/MaleHair/FG_Male01HairDefaults.dae</model>
        <shapes>Male_PartLeftShape</shapes>
    </hair>
    <hair>
        <name>Male_ShortMessyShape</name>
        <model>assets/models/collada/Hair/MaleHair/FG_Male01HairDefaults.dae</model>
        <shapes>Male_ShortMessyShape</shapes>
    </hair>
    <hair>
        <name>Male_FlatTopShape</name>
        <model>assets/models/collada/Hair/MaleHair/FG_Male01HairDefaults.dae</model>
        <shapes>Male_FlatTopShape</shapes>
    </hair>
    <hair>
        <name>Male_ShortTopUpShape</name>
        <model>assets/models/collada/Hair/MaleHair/FG_Male01HairDefaults.dae</model>
        <shapes>Male_ShortTopUpShape</shapes>
    </hair>
    <hair>
        <name>Male_ShortBasicShape</name>
        <model>assets/models/collada/Hair/MaleHair/FG_Male01HairDefaults.dae</model>
        <shapes>Male_ShortBasicShape</shapes>
    </hair>
    <hair>
        <name>Male_ShortRecedShape</name>
        <model>assets/models/collada/Hair/MaleHair/FG_Male01HairDefaults.dae</model>
        <shapes>Male_ShortRecedShape</shapes>
    </hair>
    <hair>
        <name>Male_Balding1Shape</name>
        <model>assets/models/collada/Hair/MaleHair/FG_Male01HairDefaults.dae</model>
        <shapes>Male_Balding1Shape</shapes>
    </hair>
    <hair>
        <name>Male_BaldPiccardShape</name>
        <model>assets/models/collada/Hair/MaleHair/FG_Male01HairDefaults.dae</model>
        <shapes>Male_BaldPiccardShape</shapes>
    </hair>
    <hair>
        <name>Male_SuperFauxHawkShape</name>
        <model>assets/models/collada/Hair/MaleHair/FG_Male01HairDefaults.dae</model>
        <shapes>Male_SuperFauxHawkShape</shapes>
    </hair>
    <hair>
        <name>Male_SpikeyShape</name>
        <model>assets/models/collada/Hair/MaleHair/FG_Male01HairDefaults.dae</model>
        <shapes>Male_SpikeyShape</shapes>
    </hair>
    <hair>
        <name>Male_ChinLengthPartRightShape</name>
        <model>assets/models/collada/Hair/MaleHair/FG_Male01HairDefaults.dae</model>
        <shapes>Male_ChinLengthPartRightShape</shapes>
    </hair>
    <hair>
        <name>Male_PartRightShape</name>
        <model>assets/models/collada/Hair/MaleHair/FG_Male01HairDefaults.dae</model>
        <shapes>Male_PartRightShape</shapes>
    </hair>

    <!-- HANDS -->
    <hands>
        <name>Hands</name>
        <model>assets/models/collada/Avatars/MaleAvatar/Male_Hands.dae</model>
        <shapes>RHandShape</shapes>
        <shapes>LHandShape</shapes>
    </hands>

    <!-- TORSOS -->
    <torsos>
        <name>T Shirt</name>
        <model>assets/models/collada/Clothing/MaleClothing/MaleTShirt.dae</model>
        <shapes>PoloShape</shapes>
        <shapes>ArmsShape</shapes>
    </torsos>
    <torsos>
        <name>Polo</name>
        <model>assets/models/collada/Clothing/MaleClothing/MalePolo.dae</model>
        <shapes>PoloShape</shapes>
        <shapes>TorsoNudeShape</shapes>
    </torsos>
    <torsos>
        <name>Dress Shirt</name>
        <model>assets/models/collada/Clothing/MaleClothing/MaleDressShirt.dae</model>
        <shapes>DressShirtShape</shapes>
    </torsos>
    <torsos>
        <name>Sweater</name>
        <model>assets/models/collada/Clothing/MaleClothing/MaleSweater.dae</model>
        <shapes>SweaterMaleShape</shapes>
    </torsos>
    <torsos>
        <name>Suit Shirt</name>
        <model>assets/models/collada/Clothing/MaleClothing/SuitDressShirt.dae</model>
        <shapes>SuitShirtShape</shapes>
    </torsos>
    <torsos>
        <name>Meso</name>
        <model>assets/models/collada/Clothing/MaleClothing/MaleMesoTop.dae</model>
        <shapes>TorsoNudeShape</shapes>
        <shapes>polySurfaceShape2</shapes>
    </torsos>

    <!-- JACKETS -->
    <jackets>
        <name>No Jacket</name>
    </jackets>
    <jackets>
        <name>Suit Jacket</name>
        <model>assets/models/collada/Clothing/MaleClothing/SuitJacket.dae</model>
        <shapes>SuitJacketShape</shapes>
    </jackets>
    
    <!-- FEET -->
    <feet>
        <name>Tennis Shoes</name>
        <model>assets/models/collada/Clothing/MaleClothing/MaleTennisShoes.dae</model>
        <shapes>TennisShoesShape</shapes>
    </feet>
    <feet>
        <name>Flip Flops</name>
        <model>assets/models/collada/Clothing/MaleClothing/FlipFlopsFeet.dae</model>
        <shapes>LFootNudeShape</shapes>
        <shapes>RFootNudeShape</shapes>
        <shapes>LFlipFlopShape</shapes>
        <shapes>RFlipFlopShape</shapes>
    </feet>
    <feet>
        <name>Dress Shoes</name>
        <model>assets/models/collada/Clothing/MaleClothing/MaleDressShoes.dae</model>
        <shapes>polySurfaceShape3</shapes>
    </feet>
    <feet>
        <name>Cowboy Boots</name>
        <model>assets/models/collada/Clothing/MaleClothing/CowBoyBoot_CUT.dae</model>
        <shapes>CowBoyBootsShape</shapes>
    </feet>
    <feet>
        <name>Bare Feet</name>
        <model>assets/models/collada/Avatars/MaleAvatar/Male_Bind.dae</model>
        <shapes>RFootNudeShape</shapes>
        <shapes>LFootNudeShape</shapes>
    </feet>

    <!-- LEGS -->
    <legs>
        <name>Jeans</name>
        <model>assets/models/collada/Clothing/MaleClothing/Jeans.dae</model>
        <shapes>polySurface3Shape</shapes>
    </legs>
    <legs>
        <name>Shorts</name>
        <model>assets/models/collada/Clothing/MaleClothing/Shorts.dae</model>
        <shapes>LegsNudeShape</shapes>
        <shapes>MaleShortsShape</shapes>
    </legs>
    <legs>
        <name>Dress Pants</name>
        <model>assets/models/collada/Clothing/MaleClothing/MaleDressPants1.dae</model>
        <shapes>MaleDressPantsShape</shapes>
    </legs>
    <legs>
        <name>Slacks</name>
        <model>assets/models/collada/Clothing/MaleClothing/Slacks.dae</model>
        <shapes>SuitPantsShape</shapes>
    </legs>
    <legs>
        <name>Meso</name>
        <model>assets/models/collada/Clothing/MaleClothing/MaleMesoBottom.dae</model>
        <shapes>LegsNudeShape</shapes>
        <shapes>polySurfaceShape6</shapes>
    </legs>
</config-list>